Metadata-Version: 2.1
Name: simStatus
Version: 1.0.9
Summary: UNKNOWN
Home-page: https://github.com/Khalil-Youssefi/simStatus
Author: Khalil Youssefi
Author-email: kh4lil@outlook.com
License: UNKNOWN
Platform: UNKNOWN
Requires-Python: >=3.6
License-File: LICENSE
